nmcipher/transposition/__init__.py
nmcipher/transposition/columnar.py
nmcipher.transposition-0.0.10.dist-info/METADATA
nmcipher.transposition-0.0.10.dist-info/WHEEL
nmcipher.transposition-0.0.10.dist-info/top_level.txt
nmcipher.transposition-0.0.10.dist-info/RECORD
