Metadata-Version: 2.1
Name: nmcipher.transposition
Version: 0.0.10
Summary: A command line parser package for use with basic encryption algorithms
Home-page: UNKNOWN
Author: Neil Marshall
Author-email: neil.marshall@dunelm.org.uk
License: UNKNOWN
Platform: UNKNOWN
Requires-Python: >=3.8
